converter/__init__.py
converter/__main__.py
converter/ann_converter.py
good_converter/__init__.py
good_converter/__main__.py
good_converter/ann_converter.py
good_converter-0.2.dist-info/LICENSE
good_converter-0.2.dist-info/METADATA
good_converter-0.2.dist-info/WHEEL
good_converter-0.2.dist-info/top_level.txt
good_converter-0.2.dist-info/RECORD
